sas7bdat_converter_cli/__init__.py
sas7bdat_converter_cli/__main__.py
sas7bdat_converter_cli/main.py
sas7bdat_converter_cli/py.typed
sas7bdat_converter_cli-2.0.0.dist-info/LICENSE
sas7bdat_converter_cli-2.0.0.dist-info/METADATA
sas7bdat_converter_cli-2.0.0.dist-info/WHEEL
sas7bdat_converter_cli-2.0.0.dist-info/entry_points.txt
sas7bdat_converter_cli-2.0.0.dist-info/RECORD
