Metadata-Version: 2.3
Name: sas7bdat-converter-cli
Version: 2.0.0
Summary: CLI to convert sas7bdat and xport files into other formats
License: MIT
Keywords: sas,sas7bdat,converter,xpt,XPort
Author: Paul Sanders
Author-email: paul@pbsdatasolutions.com
Requires-Python: >=3.10,<4.0
Classifier: Intended Audience :: Science/Research
Classifier: License :: OSI Approved :: MIT License
Classifier: Operating System :: OS Independent
Classifier: Programming Language :: Python :: 3
Classifier: Programming Language :: Python :: 3.10
Classifier: Programming Language :: Python :: 3.11
Classifier: Programming Language :: Python :: 3.12
Classifier: Programming Language :: Python :: 3.13
Classifier: Typing :: Typed
Requires-Dist: rich (==14.0.0)
Requires-Dist: sas7bdat-converter[all] (==3.0.0)
Requires-Dist: typer (==0.16.0)
Project-URL: Documentation, https://github.com/pbs-data-solutions/sas7bdat-converter-cli
Project-URL: Homepage, https://github.com/pbs-data-solutions/sas7bdat-converter-cli
Project-URL: Repository, https://github.com/pbs-data-solutions/sas7bdat-converter-cli
